<?xml version="1.0" encoding="UTF-8"?>
<jcr:root xmlns:jcr="http://www.jcp.org/jcr/1.0" xmlns:nt="http://www.jcp.org/jcr/nt/1.0" xmlns:cq="http://www.day.com/jcr/cq/1.0" xmlns:sling="http://sling.apache.org/jcr/sling/1.0"
    jcr:primaryType="cq:Page">
    <jcr:content
        cq:lastModified="{Date}2023-08-31T22:34:26.244+10:00"
        cq:lastModifiedBy="admin"
        cq:template="/conf/manawabay-showcase/settings/wcm/templates/page-content"
        jcr:primaryType="cq:PageContent"
        jcr:title="Borders"
        sling:resourceType="manawabay/components/page">
        <root
            jcr:primaryType="nt:unstructured"
            sling:resourceType="manawabay/components/container"
            layout="responsiveGrid">
            <container
                jcr:primaryType="nt:unstructured"
                sling:resourceType="manawabay/components/container"
                layout="responsiveGrid">
                <title
                    jcr:primaryType="nt:unstructured"
                    sling:resourceType="manawabay/components/title"/>
                <container
                    jcr:primaryType="nt:unstructured"
                    sling:resourceType="manawabay/components/container"
                    layout="responsiveGrid">
                    <container_484486946
                        cq:styleIds="[1691505425525,1691570009699,1691505333739]"
                        jcr:lastModified="{Date}2023-08-31T22:16:15.683+10:00"
                        jcr:lastModifiedBy="admin"
                        jcr:primaryType="nt:unstructured"
                        sling:resourceType="manawabay/components/container">
                        <container
                            cq:styleIds="[1691569933619,1693484347351,1693484673520,1693484964372]"
                            jcr:lastModified="{Date}2023-08-31T22:15:04.274+10:00"
                            jcr:lastModifiedBy="admin"
                            jcr:primaryType="nt:unstructured"
                            sling:resourceType="manawabay/components/container">
                            <cq:responsive jcr:primaryType="nt:unstructured">
                                <default
                                    jcr:primaryType="nt:unstructured"
                                    offset="0"
                                    width="3"/>
                            </cq:responsive>
                            <text
                                jcr:lastModified="{Date}2023-08-31T22:17:52.598+10:00"
                                jcr:lastModifiedBy="admin"
                                jcr:primaryType="nt:unstructured"
                                sling:resourceType="manawabay/components/text"
                                text="&lt;p>Text&lt;/p>&#xd;&#xa;"
                                textIsRich="true"/>
                        </container>
                        <container_copy_39624
                            cq:styleIds="[1691567192077,1691569933619,1693484363885,1693484942269]"
                            jcr:lastModified="{Date}2023-08-31T22:17:21.934+10:00"
                            jcr:lastModifiedBy="admin"
                            jcr:primaryType="nt:unstructured"
                            sling:resourceType="manawabay/components/container">
                            <cq:responsive jcr:primaryType="nt:unstructured">
                                <default
                                    jcr:primaryType="nt:unstructured"
                                    offset="0"
                                    width="3"/>
                            </cq:responsive>
                            <text_copy
                                jcr:lastModified="{Date}2023-08-31T22:17:52.598+10:00"
                                jcr:lastModifiedBy="admin"
                                jcr:primaryType="nt:unstructured"
                                sling:resourceType="manawabay/components/text"
                                text="&lt;p>Text&lt;/p>&#xd;&#xa;"
                                textIsRich="true"/>
                        </container_copy_39624>
                        <container_copy
                            cq:styleIds="[1691567292295,1691569891960,1693484378032,1693484955081]"
                            jcr:lastModified="{Date}2023-08-31T22:17:04.688+10:00"
                            jcr:lastModifiedBy="admin"
                            jcr:primaryType="nt:unstructured"
                            sling:resourceType="manawabay/components/container">
                            <cq:responsive jcr:primaryType="nt:unstructured">
                                <default
                                    jcr:primaryType="nt:unstructured"
                                    offset="0"
                                    width="3"/>
                            </cq:responsive>
                            <text_copy
                                jcr:lastModified="{Date}2023-08-31T22:17:52.598+10:00"
                                jcr:lastModifiedBy="admin"
                                jcr:primaryType="nt:unstructured"
                                sling:resourceType="manawabay/components/text"
                                text="&lt;p>Text&lt;/p>&#xd;&#xa;"
                                textIsRich="true"/>
                        </container_copy>
                        <container_copy_copy
                            cq:styleIds="[1691567300161,1691569891960,1693484401898,1693484964372]"
                            jcr:lastModified="{Date}2023-08-31T22:17:04.688+10:00"
                            jcr:lastModifiedBy="admin"
                            jcr:primaryType="nt:unstructured"
                            sling:resourceType="manawabay/components/container">
                            <cq:responsive jcr:primaryType="nt:unstructured">
                                <default
                                    jcr:primaryType="nt:unstructured"
                                    offset="0"
                                    width="3"/>
                            </cq:responsive>
                            <text_copy
                                jcr:lastModified="{Date}2023-08-31T22:17:52.598+10:00"
                                jcr:lastModifiedBy="admin"
                                jcr:primaryType="nt:unstructured"
                                sling:resourceType="manawabay/components/text"
                                text="&lt;p>Text&lt;/p>&#xd;&#xa;"
                                textIsRich="true"/>
                        </container_copy_copy>
                        <container_copy_copy_
                            cq:styleIds="[1691567306588,1691569891960,1693484422477]"
                            jcr:lastModified="{Date}2023-08-31T22:17:04.688+10:00"
                            jcr:lastModifiedBy="admin"
                            jcr:primaryType="nt:unstructured"
                            sling:resourceType="manawabay/components/container">
                            <cq:responsive jcr:primaryType="nt:unstructured">
                                <default
                                    jcr:primaryType="nt:unstructured"
                                    offset="0"
                                    width="3"/>
                            </cq:responsive>
                            <text_copy
                                jcr:lastModified="{Date}2023-08-31T22:17:52.598+10:00"
                                jcr:lastModifiedBy="admin"
                                jcr:primaryType="nt:unstructured"
                                sling:resourceType="manawabay/components/text"
                                text="&lt;p>Text&lt;/p>&#xd;&#xa;"
                                textIsRich="true"/>
                        </container_copy_copy_>
                    </container_484486946>
                </container>
            </container>
        </root>
    </jcr:content>
</jcr:root>
